aerial/__init__.py
aerial/_version.py
aerial/data_preparation.py
aerial/discretization.py
aerial/model.py
aerial/rule_extraction.py
aerial/rule_quality.py
aerial/table.py
pyaerial-1.0.17.dist-info/licenses/LICENSE
pyaerial-1.0.17.dist-info/METADATA
pyaerial-1.0.17.dist-info/WHEEL
pyaerial-1.0.17.dist-info/top_level.txt
pyaerial-1.0.17.dist-info/RECORD
