Metadata-Version: 2.4
Name: pyaerial
Version: 1.0.17
Summary: An implementation of the Aerial neurosymbolic association rule mining algorithm from tabular datasets.
Author-email: Erkan Karabulut <e.karabulut@uva.nl>
Project-URL: Homepage, https://github.com/DiTEC-project/pyaerial
Project-URL: Documentation, https://github.com/DiTEC-project/pyaerial
Project-URL: Source, https://github.com/DiTEC-project/pyaerial
Project-URL: Tracker, https://github.com/DiTEC-project/pyaerial/issues
Requires-Python: >=3.7
License-File: LICENSE
Requires-Dist: torch~=2.7.0
Requires-Dist: numpy~=2.0.0
Requires-Dist: joblib~=1.4.2
Requires-Dist: setuptools~=80.9.0
Requires-Dist: pytest~=8.3.5
Requires-Dist: pandas~=2.2.3
Requires-Dist: scikit-learn~=1.6.0
Dynamic: license-file
